fds/__init__.py
fds/sdk/__init__.py
fds/sdk/Signals/__init__.py
fds/sdk/Signals/api_client.py
fds/sdk/Signals/configuration.py
fds/sdk/Signals/exceptions.py
fds/sdk/Signals/model_utils.py
fds/sdk/Signals/rest.py
fds/sdk/Signals/api/__init__.py
fds/sdk/Signals/api/events_api.py
fds/sdk/Signals/api/metadata_api.py
fds/sdk/Signals/apis/__init__.py
fds/sdk/Signals/model/__init__.py
fds/sdk/Signals/model/contract.py
fds/sdk/Signals/model/contract_fields.py
fds/sdk/Signals/model/contract_fields_event_date.py
fds/sdk/Signals/model/contract_fields_summary.py
fds/sdk/Signals/model/contract_property.py
fds/sdk/Signals/model/contract_property_items.py
fds/sdk/Signals/model/date_time_interval.py
fds/sdk/Signals/model/error_item.py
fds/sdk/Signals/model/error_item_source.py
fds/sdk/Signals/model/error_response.py
fds/sdk/Signals/model/event_adaptive_card.py
fds/sdk/Signals/model/event_adaptive_cards.py
fds/sdk/Signals/model/event_adaptive_data_item.py
fds/sdk/Signals/model/event_detail.py
fds/sdk/Signals/model/event_detail_data_item.py
fds/sdk/Signals/model/event_detail_data_item_all_of.py
fds/sdk/Signals/model/event_details.py
fds/sdk/Signals/model/event_headline_data_item.py
fds/sdk/Signals/model/event_headlines.py
fds/sdk/Signals/model/event_meta.py
fds/sdk/Signals/model/event_request_body.py
fds/sdk/Signals/model/events_entities.py
fds/sdk/Signals/model/events_entities_post.py
fds/sdk/Signals/model/events_meta.py
fds/sdk/Signals/model/events_meta_date_range.py
fds/sdk/Signals/model/events_meta_pagination.py
fds/sdk/Signals/model/id_resolutions_meta.py
fds/sdk/Signals/model/rate_limit_response.py
fds/sdk/Signals/model/relevance_score_range.py
fds/sdk/Signals/model/screen_meta.py
fds/sdk/Signals/model/screen_meta_partial.py
fds/sdk/Signals/model/signal_definition.py
fds/sdk/Signals/model/signal_definition_data.py
fds/sdk/Signals/model/signal_meta_data.py
fds/sdk/Signals/model/signal_meta_data_data.py
fds/sdk/Signals/models/__init__.py
fds.sdk.Signals-1.0.2.dist-info/LICENSE
fds.sdk.Signals-1.0.2.dist-info/METADATA
fds.sdk.Signals-1.0.2.dist-info/WHEEL
fds.sdk.Signals-1.0.2.dist-info/top_level.txt
fds.sdk.Signals-1.0.2.dist-info/RECORD
